brownieSorter/__init__.py
brownieSorter/brownieSorter.py
brownieSort-0.0.1.dist-info/LICENSE
brownieSort-0.0.1.dist-info/METADATA
brownieSort-0.0.1.dist-info/WHEEL
brownieSort-0.0.1.dist-info/top_level.txt
brownieSort-0.0.1.dist-info/RECORD
