Metadata-Version: 2.1
Name: brownieSort
Version: 0.0.1
Summary: For sorting brownies into tent groups
Home-page: https://github.com/apeden/brownieSorter
Author: Alex Peden
Author-email: apeden23@gmail.com
License: UNKNOWN
Platform: UNKNOWN
Classifier: Programming Language :: Python :: 3
Classifier: License :: OSI Approved :: MIT License
Classifier: Operating System :: OS Independent
